{
    "Abyssinian": "阿比西尼亞貓",
    "affenpinscher": "艾芬品犬",
    "Afghan_hound": "阿富汗獵犬",
    "African_hunting_dog": "非洲獵犬",
    "Airedale": "艾爾戴爾梗",
    "american_bulldog": "美國鬥牛犬",
    "american_pit_bull_terrier": "美國比特鬥牛梗",
    "American_Staffordshire_terrier": "美國斯塔福郡梗",
    "Appenzeller": "阿彭策爾山犬",
    "Australian_terrier": "澳洲梗",
    "basenji": "巴仙吉犬",
    "basset": "巴吉度獵犬",
    "basset_hound": "巴吉度獵犬",
    "beagle": "米格魯",
    "Bedlington_terrier": "貝林頓梗",
    "Bengal": "孟加拉貓",
    "Bernese_mountain_dog": "伯恩山犬",
    "Birman": "緬因貓",
    "black-and-tan_coonhound": "黑褐浣熊獵犬",
    "Blenheim_spaniel": "布倫海姆獵犬",
    "bloodhound": "尋血獵犬",
    "bluetick": "藍色斑點獵犬",
    "Bombay": "孟買貓",
    "Border_collie": "邊境牧羊犬",
    "Border_terrier": "邊境梗",
    "borzoi": "俄羅斯獵狼犬",
    "Boston_bull": "波士頓梗犬",
    "Bouvier_des_Flandres": "法蘭德斯畜牧犬",
    "boxer": "拳師犬",
    "Brabancon_griffon": "布魯塞爾格里芬犬",
    "briard": "布里牧羊犬",
    "British_Shorthair": "英國短毛貓",
    "Brittany_spaniel": "布列塔尼獵犬",
    "bull_mastiff": "鬥牛獒犬",
    "cairn": "凱恩梗",
    "Cardigan": "卡迪根威爾士柯基",
    "Chesapeake_Bay_retriever": "切薩皮克灣獵犬",
    "Chihuahua": "吉娃娃",
    "chow": "鬆獅犬",
    "clumber": "克倫伯獵犬",
    "cocker_spaniel": "可卡犬",
    "collie": "柯利犬",
    "curly-coated_retriever": "捲毛尋回犬",
    "Dandie_Dinmont": "丹第丁蒙梗",
    "dhole": "亞洲野犬",
    "dingo": "澳洲野犬",
    "Doberman": "杜賓犬",
    "english_cocker_spaniel": "英國可卡犬",
    "English_foxhound": "英國獵狐犬",
    "English_setter": "英國雪達犬",
    "English_springer": "英國跳獵犬",
    "Engyptian_Mau": "埃及貓",
    "EntleBucher": "恩特布赫山犬",
    "Eskimo_dog": "愛斯基摩犬",
    "flat-coated_retriever": "平毛尋回犬",
    "French_bulldog": "法國鬥牛犬",
    "German_shepherd": "德國牧羊犬",
    "German_short-haired_pointer": "德國短毛指標犬",
    "german_shorthaired": "德國短毛指標犬",
    "giant_schnauzer": "巨型雪納瑞",
    "golden_retriever": "黃金獵犬",
    "Gordon_setter": "戈登雪達犬",
    "Greater_Swiss_Mountain_dog": "大瑞士山犬",
    "Great_Dane": "大丹犬",
    "Great_Pyrenees": "大白熊犬",
    "groenendael": "比利時格羅安達犬",
    "havanese": "哈瓦那犬",
    "Ibizan_hound": "伊比薩獵犬",
    "Irish_setter": "愛爾蘭雪達犬",
    "Irish_terrier": "愛爾蘭梗",
    "Irish_water_spaniel": "愛爾蘭水獵犬",
    "Irish_wolfhound": "愛爾蘭獵狼犬",
    "Italian_greyhound": "義大利靈緹犬",
    "japanese_chin": "日本狆犬",
    "Japanese_spaniel": "日本狆犬",
    "keeshond": "荷蘭凱斯犬",
    "kelpie": "澳洲凱爾皮犬",
    "Kerry_blue_terrier": "凱利藍梗",
    "komondor": "匈牙利牧羊犬",
    "kuvasz": "庫瓦茲犬",
    "Labrador_retriever": "拉布拉多獵犬",
    "Lakeland_terrier": "湖區梗",
    "Leonberg": "萊昂貝格犬",
    "leonberger": "萊昂貝格犬",
    "Lhasa": "拉薩犬",
    "Maine_Coon": "緬因貓",
    "malamute": "阿拉斯加雪橇犬",
    "malinois": "比利時瑪利諾犬",
    "Maltese_dog": "馬爾濟斯犬",
    "Mexican_hairless": "墨西哥無毛犬",
    "miniature_pinscher": "迷你品犬",
    "miniature_poodle": "迷你貴賓犬",
    "miniature_schnauzer": "迷你雪納瑞",
    "Newfoundland": "紐芬蘭犬",
    "Norfolk_terrier": "諾福克梗",
    "Norwegian_elkhound": "挪威獵犬",
    "Norwich_terrier": "諾里奇梗",
    "Old_English_sheepdog": "英國古代牧羊犬",
    "otterhound": "水獺獵犬",
    "papillon": "蝶耳犬",
    "Pekinese": "北京犬",
    "Pembroke": "彭布羅克威爾士柯基",
    "Persian": "波斯貓",
    "Pomeranian": "博美犬",
    "pug": "巴哥犬",
    "redbone": "紅骨獵犬",
    "Regdoll": "布偶貓",
    "Rhodesian_ridgeback": "羅得西亞脊背犬",
    "Rottweiler": "羅威納犬",
    "Russian_Blue": "俄羅斯藍貓",
    "Saint_Bernard": "聖伯納犬",
    "Saluki": "薩路基獵犬",
    "Samoyed": "薩摩耶犬",
    "schipperke": "史奇派克犬",
    "Scotch_terrier": "蘇格蘭梗",
    "Scottish_deerhound": "蘇格蘭獵鹿犬",
    "scottish_terrier": "蘇格蘭梗",
    "Sealyham_terrier": "西利漢梗",
    "Shetland_sheepdog": "喜樂蒂牧羊犬",
    "shiba_inu": "柴犬",
    "Shih-Tzu": "西施犬",
    "Siamese": "暹羅貓",
    "Siberian_husky": "西伯利亞哈士奇",
    "silky_terrier": "絲毛梗",
    "soft-coated_wheaten_terrier": "軟毛小麥梗",
    "Staffordshire_bull_terrier": "斯塔福郡鬥牛梗",
    "mydog": "我的寶貝狗勾",
    "standard_poodle": "標準貴賓犬",
    "standard_schnauzer": "標準雪納瑞",
    "Sussex_spaniel": "薩塞克斯獵犬",
    "Syhynx": "斯芬克斯貓",
    "Tibetan_mastiff": "藏獒",
    "Tibetan_terrier": "西藏梗",
    "toy_poodle": "玩具貴賓犬",
    "toy_terrier": "玩具梗",
    "vizsla": "維茲拉犬",
    "Walker_hound": "沃克獵犬",
    "Weimaraner": "魏瑪犬",
    "Welsh_springer_spaniel": "威爾士跳獵犬",
    "West_Highland_white_terrier": "西高地白梗",
    "whippet": "惠比特犬",
    "wire-haired_fox_terrier": "剛毛獵狐梗",
    "Yorkshire_terrier": "約克夏梗"
  }